CheckVersionW10/Funciones.py
CheckVersionW10/__init__.py
CheckVersionW10-2.4.6.dist-info/METADATA
CheckVersionW10-2.4.6.dist-info/WHEEL
CheckVersionW10-2.4.6.dist-info/top_level.txt
CheckVersionW10-2.4.6.dist-info/RECORD
