Metadata-Version: 2.1
Name: CheckVersionW10
Version: 2.4.6
Summary: Librería para Validar Fecha de Librerias de Windows 10
Home-page: https://github.com/AHernanandez1234/
Author: Arturo Hernandez
Author-email: ahernandez1980ene@gmail.com
License: MIT
Requires-Dist: datetime
